inspector/__init__.py
inspector/configuration.py
inspector/inspector.py
inspector/exceptions/__init__.py
inspector/exceptions/inspector_exception.py
inspector/models/__init__.py
inspector/models/arrayable.py
inspector/models/error.py
inspector/models/has_context.py
inspector/models/performance.py
inspector/models/segment.py
inspector/models/transaction.py
inspector/models/enums/__init__.py
inspector/models/enums/model_type.py
inspector/models/enums/transaction_type.py
inspector/models/enums/transport_type.py
inspector/models/partials/__init__.py
inspector/models/partials/host.py
inspector/models/partials/http.py
inspector/models/partials/request.py
inspector/models/partials/socket.py
inspector/models/partials/url.py
inspector/models/partials/user.py
inspector/transports/__init__.py
inspector/transports/async_transport.py
inspector/transports/sync_transport.py
inspector/transports/transport.py
inspector/transports/transport_interface.py
tests/__init__.py
tests/test_agent.py
tests/test_exception_encoder.py
inspector_python-0.2.0.dist-info/LICENSE
inspector_python-0.2.0.dist-info/METADATA
inspector_python-0.2.0.dist-info/WHEEL
inspector_python-0.2.0.dist-info/top_level.txt
inspector_python-0.2.0.dist-info/RECORD
