Metadata-Version: 2.1
Name: inspector-python
Version: 0.2.0
Summary: Real-time Code Execution Monitoring of Python applications.
Home-page: https://inspector.dev/
Author: Inspector
Author-email: support@inspector.dev
License: MIT
Project-URL: Documentation, https://docs.inspector.dev/guides/python/
Project-URL: Source Code, https://github.com/inspector-apm/inspector-python
Project-URL: Issue Tracker, https://github.com/inspector-apm/inspector-python/issues
License-File: LICENSE
Provides-Extra: tests
Requires-Dist: pytest ; extra == 'tests'
